onespacemedia_server_management-3.1.0.dist-info/METADATA
onespacemedia_server_management-3.1.0.dist-info/RECORD
onespacemedia_server_management-3.1.0.dist-info/WHEEL
onespacemedia_server_management-3.1.0.dist-info/top_level.txt
server_management/__init__.py
server_management/management/__init__.py
server_management/management/commands/__init__.py
server_management/management/commands/_core.py
server_management/management/commands/backupdb.py
server_management/management/commands/deploy.py
server_management/management/commands/pulldb.py
server_management/management/commands/pullmedia.py
server_management/management/commands/pushdb.py
server_management/management/commands/pushmedia.py
server_management/management/commands/ssl.py
server_management/management/commands/update.py
server_management/templates/apt_periodic
server_management/templates/certbot_cronjob
server_management/templates/nginx_production
server_management/templates/nginx_staging
server_management/templates/supervisor_config
server_management/templates/supervisor_init
